basis_theory/__init__.py
basis_theory/account_updater/__init__.py
basis_theory/account_updater/client.py
basis_theory/account_updater/jobs/__init__.py
basis_theory/account_updater/jobs/client.py
basis_theory/account_updater/jobs/raw_client.py
basis_theory/account_updater/raw_client.py
basis_theory/account_updater/real_time/__init__.py
basis_theory/account_updater/real_time/client.py
basis_theory/account_updater/real_time/raw_client.py
basis_theory/apple_pay/__init__.py
basis_theory/apple_pay/client.py
basis_theory/apple_pay/domain/__init__.py
basis_theory/apple_pay/domain/client.py
basis_theory/apple_pay/domain/raw_client.py
basis_theory/apple_pay/raw_client.py
basis_theory/apple_pay/session/__init__.py
basis_theory/apple_pay/session/client.py
basis_theory/apple_pay/session/raw_client.py
basis_theory/application_keys/__init__.py
basis_theory/application_keys/client.py
basis_theory/application_keys/raw_client.py
basis_theory/application_templates/__init__.py
basis_theory/application_templates/client.py
basis_theory/application_templates/raw_client.py
basis_theory/applications/__init__.py
basis_theory/applications/client.py
basis_theory/applications/raw_client.py
basis_theory/client.py
basis_theory/core/__init__.py
basis_theory/core/api_error.py
basis_theory/core/client_wrapper.py
basis_theory/core/datetime_utils.py
basis_theory/core/file.py
basis_theory/core/force_multipart.py
basis_theory/core/http_client.py
basis_theory/core/http_response.py
basis_theory/core/jsonable_encoder.py
basis_theory/core/pagination.py
basis_theory/core/pydantic_utilities.py
basis_theory/core/query_encoder.py
basis_theory/core/remove_none_from_dict.py
basis_theory/core/request_options.py
basis_theory/core/serialization.py
basis_theory/documents/__init__.py
basis_theory/documents/client.py
basis_theory/documents/data/__init__.py
basis_theory/documents/data/client.py
basis_theory/documents/data/raw_client.py
basis_theory/documents/raw_client.py
basis_theory/enrichments/__init__.py
basistheoryclient-3.1.0.dist-info/LICENSE
basistheoryclient-3.1.0.dist-info/METADATA
basistheoryclient-3.1.0.dist-info/WHEEL
basistheoryclient-3.1.0.dist-info/RECORD
